pytest_collect_appoint_info/__init__.py
pytest_collect_appoint_info-0.0.1.dist-info/LICENSE
pytest_collect_appoint_info-0.0.1.dist-info/METADATA
pytest_collect_appoint_info-0.0.1.dist-info/WHEEL
pytest_collect_appoint_info-0.0.1.dist-info/entry_points.txt
pytest_collect_appoint_info-0.0.1.dist-info/top_level.txt
pytest_collect_appoint_info-0.0.1.dist-info/RECORD
